<?xml version="1.0" encoding="ISO-8859-1" standalone="no"?>
<!DOCTYPE
	anotacion
	SYSTEM
	"http://www.ehu.es/~ljrf/resources/anotacion.dtd"
>

<anotacion
	anotador="eti1+eti2"
	fecha="23 September 2004 15:44:33"
>

<descripcion
	base_de_datos="INFOTREN2"
	lengua="español"
	tipo_habla="espontánea"
	registro="coloquial"
	tipo_discurso="tarea"
	frecuencia_kHz="8"
	codificacion="lineal"
	bits_muestra="16"
	lugar="oficina"
	canal="teléfono"
	nivel_ruido="bajo"
	fichero_audio=""
/>

<hablante id="sistema"/>

<hablante
id="usuario"
nombre="Z118"
sexo="hombre"
edad="adulto"
/>

<!-- Turno 1 sistema -->
<turno id="M_001" hablante="sistema" fichero_audio_ss="">
<t> Bienvenido al servicio de informacion de trenes ¿ En qué puedo ayudarle ? </t>
</turno>

<!-- Turno 1 usuario -->
<turno id="U_001" hablante="usuario" fichero_audio_ss="Z118_ZB7c5_T01u.ul">
<t> <d tipo="abrir"> Hola buenas </d> , he <l tipo="mal_pronunciada" palabra="estado"> estau </l> las vacaciones d<a>e</a> navidad en mi casa <p/> y quiero regresar a Madrid <n fuente="exterior" tipo="genérico"/> . </t>
</turno>

<!-- Turno 2 sistema -->
<turno id="M_002" hablante="sistema" fichero_audio_ss="">
<t> Lo siento . No he entendido bien ¿ puede repetir ? </t>
</turno>

<!-- Turno 2 usuario -->
<turno id="U_002" hablante="usuario" fichero_audio_ss="Z118_ZB7c5_T02u.ul">
<t> <n fuente="hablante" tipo="aspiración"/> <n fuente="exterior" tipo="genérico"/> <d tipo="rellenar"> A ver </d> , quiero regresar a Madrid <n fuente="exterior" tipo="genérico"/> después de pasar la<a>s</a> navidades en mi casa . </t>
</turno>

<!-- Turno 3 sistema -->
<turno id="M_003" hablante="sistema" fichero_audio_ss="">
<t> ¿ Quiere saber horarios ? </t>
</turno>

<!-- Turno 3 usuario -->
<turno id="U_003" hablante="usuario" fichero_audio_ss="Z118_ZB7c5_T03u.ul">
<t> No , quiero obtener el precio . </t>
</turno>

<!-- Turno 4 sistema -->
<turno id="M_004" hablante="sistema" fichero_audio_ss="">
<t> ¿ Qué día desea salir ? </t>
</turno>

<!-- Turno 4 usuario -->
<turno id="U_004" hablante="usuario" fichero_audio_ss="Z118_ZB7c5_T04u.ul">
<t> El día seis de enero . </t>
</turno>

<!-- Turno 5 sistema -->
<turno id="M_005" hablante="sistema" fichero_audio_ss="">
<t> Quiere saber el precio a Madrid ¿ desde Zaragoza ? </t>
</turno>

<!-- Turno 5 usuario -->
<turno id="U_005" hablante="usuario" fichero_audio_ss="Z118_ZB7c5_T05u.ul">
<t> Sí , para el viaje de ida . </t>
</turno>

<!-- Turno 6 sistema -->
<turno id="M_006" hablante="sistema" fichero_audio_ss="">
<t> Le consulto precios de Zaragoza a Madrid saliendo el jueves , día 6 de enero de 2005 . Un momento por favor . </t>
</turno>

<!-- Turno 7 sistema -->
<turno id="M_007" hablante="sistema" fichero_audio_ss="">
<t> Hay varios trenes . En clase turista , el tren más caro es un Talgo que cuesta 28 con 50 euros la ida y el más barato es un Costa_Brava que cuesta 21 con 50 euros . Recuerde que el billete de ida y vuelta siempre supone un ahorro del 20 por ciento ¿ Desea algo más ? </t>
</turno>

<!-- Turno 6 usuario -->
<turno id="U_006" hablante="usuario" fichero_audio_ss="Z118_ZB7c5_T06u.ul">
<t> <n fuente="hablante" tipo="aspiración"/> Sí , quisiera <r tipo="repetición"> <m> <l tipo="mal_pronunciada" palabra="viajar"> vajar </l> </m> <c> viajar </c> </r> en <r tipo="repetición"> <m> un <l tipo="cortada" palabra="Alaris"> a </l> </m> <s> <p/> </s> <c> un Alaris </c> </r> si fuera posible . </t>
</turno>

<!-- Turno 8 sistema -->
<turno id="M_008" hablante="sistema" fichero_audio_ss="">
<t> Lo siento . No he entendido bien ¿ puede repetir ? </t>
</turno>

<!-- Turno 7 usuario -->
<turno id="U_007" hablante="usuario" fichero_audio_ss="Z118_ZB7c5_T07u.ul">
<t> <n fuente="hablante" tipo="aspiración"/> Me gustaría viajar en un tren Alaris . </t>
</turno>

<!-- Turno 9 sistema -->
<turno id="M_009" hablante="sistema" fichero_audio_ss="">
<t> Le consulto precios de Zaragoza a Madrid en tipo tren Alaris . Un momento por favor . </t>
</turno>

<!-- Turno 10 sistema -->
<turno id="M_010" hablante="sistema" fichero_audio_ss="">
<t> No hay ningún tren que cumpla estos requerimientos ¿ Desea cambiar alguna de las características solicitadas ? </t>
</turno>

<!-- Turno 8 usuario -->
<turno id="U_008" hablante="usuario" fichero_audio_ss="Z118_ZB7c5_T08u.ul">
<t> No , <d tipo="cerrar"> muchas gracias </d> . </t>
</turno>

<!-- Turno 11 sistema -->
<turno id="M_011" hablante="sistema" fichero_audio_ss="">
<t> Gracias por utilizar este servicio . Feliz viaje . </t>
</turno>

</anotacion>
